openviking/__init__.py
openviking/agfs_manager.py
openviking/async_client.py
openviking/client.py
openviking/sync_client.py
openviking/bin/agfs-server
openviking/core/__init__.py
openviking/core/building_tree.py
openviking/core/context.py
openviking/core/directories.py
openviking/core/mcp_converter.py
openviking/core/skill_loader.py
openviking/message/__init__.py
openviking/message/message.py
openviking/message/part.py
openviking/models/__init__.py
openviking/models/embedder/__init__.py
openviking/models/embedder/base.py
openviking/models/embedder/openai_embedders.py
openviking/models/embedder/vikingdb_embedders.py
openviking/models/embedder/volcengine_embedders.py
openviking/models/vlm/__init__.py
openviking/models/vlm/base.py
openviking/models/vlm/llm.py
openviking/models/vlm/token_usage.py
openviking/models/vlm/backends/openai_vlm.py
openviking/models/vlm/backends/volcengine_vlm.py
openviking/parse/__init__.py
openviking/parse/base.py
openviking/parse/converter.py
openviking/parse/custom.py
openviking/parse/registry.py
openviking/parse/tree_builder.py
openviking/parse/vlm.py
openviking/parse/ovpack/__init__.py
openviking/parse/parsers/__init__.py
openviking/parse/parsers/base_parser.py
openviking/parse/parsers/code.py
openviking/parse/parsers/html.py
openviking/parse/parsers/markdown.py
openviking/parse/parsers/media.py
openviking/parse/parsers/pdf.py
openviking/parse/parsers/text.py
openviking/parse/resource_detector/__init__.py
openviking/parse/resource_detector/detect_info.py
openviking/parse/resource_detector/recursive.py
openviking/parse/resource_detector/size.py
openviking/parse/resource_detector/visit.py
openviking/prompts/__init__.py
openviking/prompts/manager.py
openviking/prompts/templates/compression/dedup_decision.yaml
openviking/prompts/templates/compression/memory_extraction.yaml
openviking/prompts/templates/compression/structured_summary.yaml
openviking-0.1.6.dist-info/METADATA
openviking-0.1.6.dist-info/WHEEL
openviking-0.1.6.dist-info/entry_points.txt
openviking-0.1.6.dist-info/top_level.txt
openviking-0.1.6.dist-info/RECORD
openviking-0.1.6.dist-info/licenses/LICENSE
