Metadata-Version: 2.4
Name: openviking
Version: 0.1.6
Summary: An Agent-native context database: Data in, Context out
Author-email: ByteDance <noreply@bytedance.com>
License: Apache-2.0
Project-URL: Homepage, https://github.com/volcengine/openviking
Project-URL: Documentation, https://openviking.readthedocs.io
Project-URL: Repository, https://github.com/volcengine/openviking
Project-URL: Issues, https://github.com/volcengine/openviking/issues
Classifier: Development Status :: 3 - Alpha
Classifier: Intended Audience :: Developers
Classifier: Topic :: Scientific/Engineering :: Artificial Intelligence
Classifier: Programming Language :: Python :: 3
Classifier: Programming Language :: Python :: 3.9
Classifier: Programming Language :: Python :: 3.10
Classifier: Programming Language :: Python :: 3.11
Classifier: Programming Language :: Python :: 3.12
Requires-Python: >=3.9
License-File: LICENSE
Requires-Dist: pydantic>=2.0.0
Requires-Dist: typing-extensions>=4.5.0
Requires-Dist: pyyaml>=6.0
Requires-Dist: httpx>=0.25.0
Requires-Dist: pdfplumber>=0.10.0
Requires-Dist: readabilipy>=0.2.0
Requires-Dist: markdownify>=0.11.0
Requires-Dist: openai>=1.0.0
Requires-Dist: requests>=2.28.0
Requires-Dist: json-repair>=0.25.0
Requires-Dist: pytest>=7.0.0
Requires-Dist: pytest-asyncio>=0.21.0
Requires-Dist: pytest-cov>=4.0.0
Requires-Dist: black>=23.0.0
Requires-Dist: isort>=5.12.0
Requires-Dist: mypy>=1.0.0
Requires-Dist: ruff>=0.1.0
Requires-Dist: sphinx>=7.0.0
Requires-Dist: sphinx-rtd-theme>=1.3.0
Requires-Dist: myst-parser>=2.0.0
Requires-Dist: apscheduler>=3.11.0
Requires-Dist: orjson>=3.11.4
Requires-Dist: volcengine>=1.0.212
Requires-Dist: volcengine-python-sdk[ark]>=5.0.3
Requires-Dist: pyagfs>=1.4.0
Requires-Dist: psutil>=7.2.1
Requires-Dist: fastapi>=0.128.0
Requires-Dist: uvicorn>=0.39.0
Requires-Dist: werkzeug>=3.1.4
Requires-Dist: pandas>=2.3.3
Requires-Dist: xxhash>=3.0.0
Dynamic: license-file
